shiwei_demo/__init__.py
shiwei_demo/suosuo.py
shiwei_demo-0.0.1.dist-info/LICENSE
shiwei_demo-0.0.1.dist-info/METADATA
shiwei_demo-0.0.1.dist-info/WHEEL
shiwei_demo-0.0.1.dist-info/top_level.txt
shiwei_demo-0.0.1.dist-info/RECORD
