Metadata-Version: 2.1
Name: shiwei-demo
Version: 0.0.1
Summary: shiwei is First Demo 
Home-page: https://github.com/haochuang/wechat-deleted-friends
Author: suosuo
Author-email: 1936506751@qq.com
License: MIT
Platform: UNKNOWN
